<persistence xmlns="http://java.sun.com/xml/ns/persistence"
	xmlns:xsi="http://www.w3.org/2001/XMLSchema-instance"
	xsi:schemaLocation="http://java.sun.com/xml/ns/persistence
	http://java.sun.com/xml/ns/persistence/persistence_2_0.xsd"
	version="2.0">

	<persistence-unit name="boodskap_pu">

		<provider>org.hibernate.jpa.HibernatePersistenceProvider</provider>

		<class>io.boodskap.iot.model.jpa.AbstractEntity</class>
		<class>io.boodskap.iot.model.jpa.AbstractFile</class>
		<class>io.boodskap.iot.model.jpa.AbstractGroup</class>
		<class>io.boodskap.iot.model.jpa.AbstractGroupId</class>
		<class>io.boodskap.iot.model.jpa.AbstractGroupMember</class>
		<class>io.boodskap.iot.model.jpa.AbstractNotification</class>
		<class>io.boodskap.iot.model.jpa.AbstractOTABatch</class>
		<class>io.boodskap.iot.model.jpa.AbstractOTABatchMember</class>
		<class>io.boodskap.iot.model.jpa.AbstractPerson</class>
		<class>io.boodskap.iot.model.jpa.AbstractRule</class>
		<class>io.boodskap.iot.model.jpa.AbstractSentNotification</class>
		<class>io.boodskap.iot.model.jpa.AbstractStorable</class>
		<class>io.boodskap.iot.model.jpa.Alexa</class>
		<class>io.boodskap.iot.model.jpa.AlexaId</class>
		<class>io.boodskap.iot.model.jpa.Asset</class>
		<class>io.boodskap.iot.model.jpa.AssetDevice</class>
		<class>io.boodskap.iot.model.jpa.AssetDeviceId</class>
		<class>io.boodskap.iot.model.jpa.AssetFile</class>
		<class>io.boodskap.iot.model.jpa.AssetFileId</class>
		<class>io.boodskap.iot.model.jpa.AssetGroup</class>
		<class>io.boodskap.iot.model.jpa.AssetGroupId</class>
		<class>io.boodskap.iot.model.jpa.AssetGroupMember</class>
		<class>io.boodskap.iot.model.jpa.AssetGroupMemberId</class>
		<class>io.boodskap.iot.model.jpa.AssetId</class>
		<class>io.boodskap.iot.model.jpa.BillingContact</class>
		<class>io.boodskap.iot.model.jpa.BillingContactId</class>
		<class>io.boodskap.iot.model.jpa.BillingInvoice</class>
		<class>io.boodskap.iot.model.jpa.BillingInvoiceId</class>
		<class>io.boodskap.iot.model.jpa.BillingSchedule</class>
		<class>io.boodskap.iot.model.jpa.BillingScheduleId</class>
		<class>io.boodskap.iot.model.jpa.BillingTemplateId</class>
		<class>io.boodskap.iot.model.jpa.BinaryRule</class>
		<class>io.boodskap.iot.model.jpa.BinaryRuleId</class>
		<class>io.boodskap.iot.model.jpa.CameraDevice</class>
		<class>io.boodskap.iot.model.jpa.CameraDeviceId</class>
		<class>io.boodskap.iot.model.jpa.ClassLoader</class>
		<class>io.boodskap.iot.model.jpa.Cluster</class>
		<class>io.boodskap.iot.model.jpa.ClusterId</class>
		<class>io.boodskap.iot.model.jpa.ClusterLicense</class>
		<class>io.boodskap.iot.model.jpa.ClusterLicenseId</class>
		<class>io.boodskap.iot.model.jpa.ClusterMachine</class>
		<class>io.boodskap.iot.model.jpa.ClusterMachineId</class>
		<class>io.boodskap.iot.model.jpa.ClusterMachineNVP</class>
		<class>io.boodskap.iot.model.jpa.ClusterMachineNVPId</class>
		<class>io.boodskap.iot.model.jpa.Counter</class>
		<class>io.boodskap.iot.model.jpa.DatabaseMetaData</class>
		<class>io.boodskap.iot.model.jpa.DatabaseMetaDataId</class>
		<class>io.boodskap.iot.model.jpa.DatabaseTable</class>
		<class>io.boodskap.iot.model.jpa.DatabaseTableField</class>
		<class>io.boodskap.iot.model.jpa.DatabaseTableFieldId</class>
		<class>io.boodskap.iot.model.jpa.DatabaseTableId</class>
		<class>io.boodskap.iot.model.jpa.Device</class>
		<class>io.boodskap.iot.model.jpa.DeviceCommand</class>
		<class>io.boodskap.iot.model.jpa.DeviceCommandId</class>
		<class>io.boodskap.iot.model.jpa.DeviceCounter</class>
		<class>io.boodskap.iot.model.jpa.DeviceCounterId</class>
		<class>io.boodskap.iot.model.jpa.DeviceFile</class>
		<class>io.boodskap.iot.model.jpa.DeviceFileId</class>
		<class>io.boodskap.iot.model.jpa.DeviceFriend</class>
		<class>io.boodskap.iot.model.jpa.DeviceFriendId</class>
		<class>io.boodskap.iot.model.jpa.DeviceGroup</class>
		<class>io.boodskap.iot.model.jpa.DeviceGroupId</class>
		<class>io.boodskap.iot.model.jpa.DeviceGroupMember</class>
		<class>io.boodskap.iot.model.jpa.DeviceGroupMemberId</class>
		<class>io.boodskap.iot.model.jpa.DeviceId</class>
		<class>io.boodskap.iot.model.jpa.DeviceMessageCounter</class>
		<class>io.boodskap.iot.model.jpa.DeviceMessageCounterId</class>
		<class>io.boodskap.iot.model.jpa.DeviceModel</class>
		<class>io.boodskap.iot.model.jpa.DeviceModelId</class>
		<class>io.boodskap.iot.model.jpa.Domain</class>
		<class>io.boodskap.iot.model.jpa.DomainAccess</class>
		<class>io.boodskap.iot.model.jpa.DomainAccessId</class>
		<class>io.boodskap.iot.model.jpa.DomainApiKey</class>
		<class>io.boodskap.iot.model.jpa.DomainApiKeyId</class>
		<class>io.boodskap.iot.model.jpa.DomainAssetGroup</class>
		<class>io.boodskap.iot.model.jpa.DomainAssetGroupId</class>
		<class>io.boodskap.iot.model.jpa.DomainAssetGroupMember</class>
		<class>io.boodskap.iot.model.jpa.DomainAssetGroupMemberId</class>
		<class>io.boodskap.iot.model.jpa.DomainClassLoader</class>
		<class>io.boodskap.iot.model.jpa.DomainClassLoaderId</class>
		<class>io.boodskap.iot.model.jpa.DomainDeviceGroup</class>
		<class>io.boodskap.iot.model.jpa.DomainDeviceGroupId</class>
		<class>io.boodskap.iot.model.jpa.DomainDeviceGroupMember</class>
		<class>io.boodskap.iot.model.jpa.DomainDeviceGroupMemberId</class>
		<class>io.boodskap.iot.model.jpa.DomainEntity</class>
		<class>io.boodskap.iot.model.jpa.DomainEntityId</class>
		<class>io.boodskap.iot.model.jpa.DomainEntityRole</class>
		<class>io.boodskap.iot.model.jpa.DomainEntityRoleId</class>
		<class>io.boodskap.iot.model.jpa.DomainFile</class>
		<class>io.boodskap.iot.model.jpa.DomainFileId</class>
		<class>io.boodskap.iot.model.jpa.DomainGroovyArchiveFile</class>
		<class>io.boodskap.iot.model.jpa.DomainGroovyArchiveFileId</class>
		<class>io.boodskap.iot.model.jpa.DomainGroovyClass</class>
		<class>io.boodskap.iot.model.jpa.DomainGroovyClassId</class>
		<class>io.boodskap.iot.model.jpa.DomainJarClass</class>
		<class>io.boodskap.iot.model.jpa.DomainJarClassId</class>
		<class>io.boodskap.iot.model.jpa.DomainJarFile</class>
		<class>io.boodskap.iot.model.jpa.DomainJarFileId</class>
		<class>io.boodskap.iot.model.jpa.DomainLicense</class>
		<class>io.boodskap.iot.model.jpa.DomainNode</class>
		<class>io.boodskap.iot.model.jpa.DomainNodeId</class>
		<class>io.boodskap.iot.model.jpa.DomainRole</class>
		<class>io.boodskap.iot.model.jpa.DomainRoleId</class>
		<class>io.boodskap.iot.model.jpa.DomainRule</class>
		<class>io.boodskap.iot.model.jpa.DomainUserGroup</class>
		<class>io.boodskap.iot.model.jpa.DomainUserGroupId</class>
		<class>io.boodskap.iot.model.jpa.DomainUserGroupMember</class>
		<class>io.boodskap.iot.model.jpa.DomainUserGroupMemberId</class>
		<class>io.boodskap.iot.model.jpa.DynamicField</class>
		<class>io.boodskap.iot.model.jpa.DynamicMessageField</class>
		<class>io.boodskap.iot.model.jpa.DynamicMessageFieldId</class>
		<class>io.boodskap.iot.model.jpa.DynamicRecordField</class>
		<class>io.boodskap.iot.model.jpa.DynamicRecordFieldId</class>
		<class>io.boodskap.iot.model.jpa.EmailGateway</class>
		<class>io.boodskap.iot.model.jpa.EntityFile</class>
		<class>io.boodskap.iot.model.jpa.EntityFileId</class>
		<class>io.boodskap.iot.model.jpa.Event</class>
		<class>io.boodskap.iot.model.jpa.EventId</class>
		<class>io.boodskap.iot.model.jpa.EventRegistration</class>
		<class>io.boodskap.iot.model.jpa.EventRegistrationId</class>
		<class>io.boodskap.iot.model.jpa.FCMDevice</class>
		<class>io.boodskap.iot.model.jpa.FCMDeviceId</class>
		<class>io.boodskap.iot.model.jpa.FCMGateway</class>
		<class>io.boodskap.iot.model.jpa.FileContent</class>
		<class>io.boodskap.iot.model.jpa.Firmware</class>
		<class>io.boodskap.iot.model.jpa.FirmwareId</class>
		<class>io.boodskap.iot.model.jpa.GlobalData</class>
		<class>io.boodskap.iot.model.jpa.GlobalDataId</class>
		<class>io.boodskap.iot.model.jpa.GroovyArchiveFile</class>
		<class>io.boodskap.iot.model.jpa.GroovyArchiveFileId</class>
		<class>io.boodskap.iot.model.jpa.GroovyClass</class>
		<class>io.boodskap.iot.model.jpa.GroovyClassId</class>
		<class>io.boodskap.iot.model.jpa.JarClass</class>
		<class>io.boodskap.iot.model.jpa.JarClassId</class>
		<class>io.boodskap.iot.model.jpa.JarFile</class>
		<class>io.boodskap.iot.model.jpa.JarFileId</class>
		<class>io.boodskap.iot.model.jpa.LinkedDomain</class>
		<class>io.boodskap.iot.model.jpa.LinkedDomainId</class>
		<class>io.boodskap.iot.model.jpa.Location</class>
		<class>io.boodskap.iot.model.jpa.LocationHistory</class>
		<class>io.boodskap.iot.model.jpa.LocationHistoryId</class>
		<class>io.boodskap.iot.model.jpa.LocationId</class>
		<class>io.boodskap.iot.model.jpa.Lookup</class>
		<class>io.boodskap.iot.model.jpa.LookupId</class>
		<class>io.boodskap.iot.model.jpa.Message</class>
		<class>io.boodskap.iot.model.jpa.MessageField</class>
		<class>io.boodskap.iot.model.jpa.MessageId</class>
		<class>io.boodskap.iot.model.jpa.MessageRule</class>
		<class>io.boodskap.iot.model.jpa.MessageRuleId</class>
		<class>io.boodskap.iot.model.jpa.MessageSpecification</class>
		<class>io.boodskap.iot.model.jpa.MessageSpecificationId</class>
		<class>io.boodskap.iot.model.jpa.NamedRule</class>
		<class>io.boodskap.iot.model.jpa.NamedRuleId</class>
		<class>io.boodskap.iot.model.jpa.NodeScheduledRule</class>
		<class>io.boodskap.iot.model.jpa.NodeScheduledRuleId</class>
		<class>io.boodskap.iot.model.jpa.OTABatch</class>
		<class>io.boodskap.iot.model.jpa.OTABatchId</class>
		<class>io.boodskap.iot.model.jpa.OTABatchMember</class>
		<class>io.boodskap.iot.model.jpa.OTABatchMemberId</class>
		<class>io.boodskap.iot.model.jpa.OTADeviceBatch</class>
		<class>io.boodskap.iot.model.jpa.OTADeviceBatchId</class>
		<class>io.boodskap.iot.model.jpa.OTADeviceBatchMember</class>
		<class>io.boodskap.iot.model.jpa.OTADeviceBatchMemberId</class>
		<class>io.boodskap.iot.model.jpa.OTAModelBatch</class>
		<class>io.boodskap.iot.model.jpa.OTAModelBatchId</class>
		<class>io.boodskap.iot.model.jpa.OTAModelBatchMember</class>
		<class>io.boodskap.iot.model.jpa.OTAModelBatchMemberId</class>
		<class>io.boodskap.iot.model.jpa.OTAModelVersionBatch</class>
		<class>io.boodskap.iot.model.jpa.OTAModelVersionBatchId</class>
		<class>io.boodskap.iot.model.jpa.OTAModelVersionBatchMember</class>
		<class>io.boodskap.iot.model.jpa.OTAModelVersionBatchMemberId</class>
		<class>io.boodskap.iot.model.jpa.OfflineSnap</class>
		<class>io.boodskap.iot.model.jpa.OfflineSnapId</class>
		<class>io.boodskap.iot.model.jpa.OfflineStream</class>
		<class>io.boodskap.iot.model.jpa.OfflineStreamId</class>
		<class>io.boodskap.iot.model.jpa.OfflineStreamSession</class>
		<class>io.boodskap.iot.model.jpa.OfflineStreamSessionId</class>
		<class>io.boodskap.iot.model.jpa.Organization</class>
		<class>io.boodskap.iot.model.jpa.OrganizationAsset</class>
		<class>io.boodskap.iot.model.jpa.OrganizationAssetId</class>
		<class>io.boodskap.iot.model.jpa.OrganizationDevice</class>
		<class>io.boodskap.iot.model.jpa.OrganizationDeviceId</class>
		<class>io.boodskap.iot.model.jpa.OrganizationFile</class>
		<class>io.boodskap.iot.model.jpa.OrganizationFileId</class>
		<class>io.boodskap.iot.model.jpa.OrganizationId</class>
		<class>io.boodskap.iot.model.jpa.OrganizationRole</class>
		<class>io.boodskap.iot.model.jpa.OrganizationRoleId</class>
		<class>io.boodskap.iot.model.jpa.OrganizationUser</class>
		<class>io.boodskap.iot.model.jpa.OrganizationUserId</class>
		<class>io.boodskap.iot.model.jpa.OrganizationUserRole</class>
		<class>io.boodskap.iot.model.jpa.OrganizationUserRoleId</class>
		<class>io.boodskap.iot.model.jpa.OutgoingCommand</class>
		<class>io.boodskap.iot.model.jpa.OutgoingCommandId</class>
		<class>io.boodskap.iot.model.jpa.OutgoingEmail</class>
		<class>io.boodskap.iot.model.jpa.OutgoingEmailId</class>
		<class>io.boodskap.iot.model.jpa.OutgoingFCM</class>
		<class>io.boodskap.iot.model.jpa.OutgoingFCMId</class>
		<class>io.boodskap.iot.model.jpa.OutgoingSms</class>
		<class>io.boodskap.iot.model.jpa.OutgoingSmsId</class>
		<class>io.boodskap.iot.model.jpa.OutgoingVoice</class>
		<class>io.boodskap.iot.model.jpa.OutgoingVoiceId</class>
		<class>io.boodskap.iot.model.jpa.Plugin</class>
		<class>io.boodskap.iot.model.jpa.PluginId</class>
		<class>io.boodskap.iot.model.jpa.Progress</class>
		<class>io.boodskap.iot.model.jpa.Property</class>
		<class>io.boodskap.iot.model.jpa.PropertyId</class>
		<class>io.boodskap.iot.model.jpa.PublicFile</class>
		<class>io.boodskap.iot.model.jpa.PublicFileId</class>
		<class>io.boodskap.iot.model.jpa.RawData</class>
		<class>io.boodskap.iot.model.jpa.RawMessage</class>
		<class>io.boodskap.iot.model.jpa.RawMessageId</class>
		<class>io.boodskap.iot.model.jpa.ReceivedCommand</class>
		<class>io.boodskap.iot.model.jpa.ReceivedCommandId</class>
		<class>io.boodskap.iot.model.jpa.ReceivedCommandNVP</class>
		<class>io.boodskap.iot.model.jpa.ReceivedCommandNVPId</class>
		<class>io.boodskap.iot.model.jpa.Record</class>
		<class>io.boodskap.iot.model.jpa.RecordField</class>
		<class>io.boodskap.iot.model.jpa.RecordId</class>
		<class>io.boodskap.iot.model.jpa.RecordSpecification</class>
		<class>io.boodskap.iot.model.jpa.RecordSpecificationId</class>
		<class>io.boodskap.iot.model.jpa.ReportedDevice</class>
		<class>io.boodskap.iot.model.jpa.ReportedDeviceId</class>
		<class>io.boodskap.iot.model.jpa.Response</class>
		<class>io.boodskap.iot.model.jpa.ScheduledRule</class>
		<class>io.boodskap.iot.model.jpa.ScheduledRuleId</class>
		<class>io.boodskap.iot.model.jpa.SentEmail</class>
		<class>io.boodskap.iot.model.jpa.SentFCM</class>
		<class>io.boodskap.iot.model.jpa.SentNotificationId</class>
		<class>io.boodskap.iot.model.jpa.SentSms</class>
		<class>io.boodskap.iot.model.jpa.SentVoice</class>
		<class>io.boodskap.iot.model.jpa.SystemFile</class>
		<class>io.boodskap.iot.model.jpa.SystemProperty</class>
		<class>io.boodskap.iot.model.jpa.SystemTemplate</class>
		<class>io.boodskap.iot.model.jpa.Template</class>
		<class>io.boodskap.iot.model.jpa.TemplateId</class>
		<class>io.boodskap.iot.model.jpa.TwilioGateway</class>
		<class>io.boodskap.iot.model.jpa.User</class>
		<class>io.boodskap.iot.model.jpa.UserAssetGroup</class>
		<class>io.boodskap.iot.model.jpa.UserAssetGroupId</class>
		<class>io.boodskap.iot.model.jpa.UserAssetGroupMember</class>
		<class>io.boodskap.iot.model.jpa.UserAssetGroupMemberId</class>
		<class>io.boodskap.iot.model.jpa.UserDeviceGroup</class>
		<class>io.boodskap.iot.model.jpa.UserDeviceGroupId</class>
		<class>io.boodskap.iot.model.jpa.UserDeviceGroupMember</class>
		<class>io.boodskap.iot.model.jpa.UserDeviceGroupMemberId</class>
		<class>io.boodskap.iot.model.jpa.UserDomain</class>
		<class>io.boodskap.iot.model.jpa.UserDomainId</class>
		<class>io.boodskap.iot.model.jpa.UserFile</class>
		<class>io.boodskap.iot.model.jpa.UserFileId</class>
		<class>io.boodskap.iot.model.jpa.UserGroup</class>
		<class>io.boodskap.iot.model.jpa.UserGroupId</class>
		<class>io.boodskap.iot.model.jpa.UserGroupMember</class>
		<class>io.boodskap.iot.model.jpa.UserGroupMemberId</class>
		<class>io.boodskap.iot.model.jpa.UserId</class>
		<class>io.boodskap.iot.model.jpa.UserRole</class>
		<class>io.boodskap.iot.model.jpa.UserRoleId</class>

	</persistence-unit>
	
</persistence>

